{
  "lastUpdate": "2026-02-13",
  "source": "TradingEconomics",
  "methodology": "Robust unit conversion: All currencies and scales normalized to USD",
  "units": {
    "gdp": "Trillions USD",
    "gdpGrowth": "Percentage (annual %)",
    "inflation": "Percentage (annual CPI %)",
    "unemployment": "Percentage (%)",
    "debt": "Percentage of GDP (%)",
    "currentAccount": "Percentage of GDP (%)",
    "production": "Percentage (annual %)",
    "tradeBalance": "Millions USD (monthly flow)"
  },
  "conversionNotes": {
    "tradeBalance": "Converted from various currencies (JPY, GBP, EUR, etc.) and scales (Million/Billion) to USD Millions",
    "gdp": "Converted from various currencies and scales to USD Trillions"
  },
  "data": {
    "gdp": 29.18,
    "gdpGrowth": 4.4,
    "inflation": 2.7,
    "unemployment": 4.3,
    "debt": 124.0,
    "currentAccount": -3.9,
    "production": 2.0,
    "tradeBalance": -56.83
  }
}